netana-3.3.1.data/scripts/cp-examples.sh
src/__init__.py
src/analize.py
src/disreport.py
src/equations.py
src/getnet.py
src/griddialog.py
src/main.py
src/mknetf.py
src/mkreport.py
src/netana.py
src/plotutil.py
src/doc/__init__.py
src/examples/__init__.py
netana-3.3.1.dist-info/METADATA
netana-3.3.1.dist-info/WHEEL
netana-3.3.1.dist-info/entry_points.txt
netana-3.3.1.dist-info/top_level.txt
netana-3.3.1.dist-info/zip-safe
netana-3.3.1.dist-info/RECORD
